{
  "statistics": {
    "detectionDate": "2023-01-12T01:57:39.329Z",
    "formats": {
      "javascript": {
        "sources": {
          "src/danielcamargo/scripts/navbar.js": {
            "lines": 12,
            "tokens": 84,
            "sources": 1,
            "clones": 0,
            "duplicatedLines": 0,
            "duplicatedTokens": 0,
            "percentage": 0,
            "percentageTokens": 0,
            "newDuplicatedLines": 0,
            "newClones": 0
          },
          "src/app.js": {
            "lines": 5,
            "tokens": 30,
            "sources": 1,
            "clones": 0,
            "duplicatedLines": 0,
            "duplicatedTokens": 0,
            "percentage": 0,
            "percentageTokens": 0,
            "newDuplicatedLines": 0,
            "newClones": 0
          },
          "tailwind.config.js": {
            "lines": 17,
            "tokens": 99,
            "sources": 1,
            "clones": 0,
            "duplicatedLines": 0,
            "duplicatedTokens": 0,
            "percentage": 0,
            "percentageTokens": 0,
            "newDuplicatedLines": 0,
            "newClones": 0
          },
          "commitlint.config.js": {
            "lines": 106,
            "tokens": 763,
            "sources": 1,
            "clones": 0,
            "duplicatedLines": 0,
            "duplicatedTokens": 0,
            "percentage": 0,
            "percentageTokens": 0,
            "newDuplicatedLines": 0,
            "newClones": 0
          },
          ".eslintrc.js": {
            "lines": 17,
            "tokens": 117,
            "sources": 1,
            "clones": 0,
            "duplicatedLines": 0,
            "duplicatedTokens": 0,
            "percentage": 0,
            "percentageTokens": 0,
            "newDuplicatedLines": 0,
            "newClones": 0
          }
        },
        "total": {
          "lines": 157,
          "tokens": 1093,
          "sources": 5,
          "clones": 0,
          "duplicatedLines": 0,
          "duplicatedTokens": 0,
          "percentage": 0,
          "percentageTokens": 0,
          "newDuplicatedLines": 0,
          "newClones": 0
        }
      },
      "markup": {
        "sources": {
          "src/tanner/index.html": {
            "lines": 13,
            "tokens": 138,
            "sources": 1,
            "clones": 0,
            "duplicatedLines": 0,
            "duplicatedTokens": 0,
            "percentage": 0,
            "percentageTokens": 0,
            "newDuplicatedLines": 0,
            "newClones": 0
          },
          "src/otavio/index.html": {
            "lines": 11,
            "tokens": 110,
            "sources": 1,
            "clones": 0,
            "duplicatedLines": 0,
            "duplicatedTokens": 0,
            "percentage": 0,
            "percentageTokens": 0,
            "newDuplicatedLines": 0,
            "newClones": 0
          },
          "src/jason/index.html": {
            "lines": 16,
            "tokens": 180,
            "sources": 1,
            "clones": 1,
            "duplicatedLines": 6,
            "duplicatedTokens": 63,
            "percentage": 37.5,
            "percentageTokens": 35,
            "newDuplicatedLines": 0,
            "newClones": 0
          },
          "src/emmanuel/index.html": {
            "lines": 11,
            "tokens": 98,
            "sources": 1,
            "clones": 0,
            "duplicatedLines": 0,
            "duplicatedTokens": 0,
            "percentage": 0,
            "percentageTokens": 0,
            "newDuplicatedLines": 0,
            "newClones": 0
          },
          "src/danielcamargo/show.html": {
            "lines": 8,
            "tokens": 79,
            "sources": 1,
            "clones": 0,
            "duplicatedLines": 0,
            "duplicatedTokens": 0,
            "percentage": 0,
            "percentageTokens": 0,
            "newDuplicatedLines": 0,
            "newClones": 0
          },
          "src/danielcamargo/index.html": {
            "lines": 20,
            "tokens": 230,
            "sources": 1,
            "clones": 0,
            "duplicatedLines": 0,
            "duplicatedTokens": 0,
            "percentage": 0,
            "percentageTokens": 0,
            "newDuplicatedLines": 0,
            "newClones": 0
          },
          "src/andres/index.html": {
            "lines": 12,
            "tokens": 124,
            "sources": 1,
            "clones": 0,
            "duplicatedLines": 0,
            "duplicatedTokens": 0,
            "percentage": 0,
            "percentageTokens": 0,
            "newDuplicatedLines": 0,
            "newClones": 0
          },
          "src/index.html": {
            "lines": 16,
            "tokens": 172,
            "sources": 1,
            "clones": 1,
            "duplicatedLines": 6,
            "duplicatedTokens": 63,
            "percentage": 37.5,
            "percentageTokens": 36.63,
            "newDuplicatedLines": 0,
            "newClones": 0
          }
        },
        "total": {
          "lines": 107,
          "tokens": 1131,
          "sources": 8,
          "clones": 1,
          "duplicatedLines": 6,
          "duplicatedTokens": 63,
          "percentage": 5.61,
          "percentageTokens": 5.57,
          "newDuplicatedLines": 0,
          "newClones": 0
        }
      },
      "css": {
        "sources": {
          "src/app.css": {
            "lines": 9,
            "tokens": 54,
            "sources": 1,
            "clones": 0,
            "duplicatedLines": 0,
            "duplicatedTokens": 0,
            "percentage": 0,
            "percentageTokens": 0,
            "newDuplicatedLines": 0,
            "newClones": 0
          }
        },
        "total": {
          "lines": 9,
          "tokens": 54,
          "sources": 1,
          "clones": 0,
          "duplicatedLines": 0,
          "duplicatedTokens": 0,
          "percentage": 0,
          "percentageTokens": 0,
          "newDuplicatedLines": 0,
          "newClones": 0
        }
      }
    },
    "total": {
      "lines": 273,
      "tokens": 2278,
      "sources": 14,
      "clones": 1,
      "duplicatedLines": 6,
      "duplicatedTokens": 63,
      "percentage": 2.2,
      "percentageTokens": 2.77,
      "newDuplicatedLines": 0,
      "newClones": 0
    }
  },
  "duplicates": [
    {
      "format": "markup",
      "lines": 7,
      "fragment": ">\n        <div x-data=\"{ open: false }\" @click.away=\"open = false\">\n            <button @click=\"open = true\">Expand</button>\n            <span x-show=\"open\"> Content... </span>\n        </div>\n    </body>\n</html>",
      "tokens": 0,
      "firstFile": {
        "name": "src/index.html",
        "start": 11,
        "end": 17,
        "startLoc": {
          "line": 11,
          "column": 2,
          "position": 109
        },
        "endLoc": {
          "line": 17,
          "column": 2,
          "position": 172
        },
        "blame": {
          "11": {
            "author": "Daniel Teleginski Camargo",
            "date": "2023-01-11 18:56:59 -0700",
            "line": "11",
            "rev": "^df71167"
          },
          "12": {
            "author": "Daniel Teleginski Camargo",
            "date": "2023-01-11 18:56:59 -0700",
            "line": "12",
            "rev": "^df71167"
          },
          "13": {
            "author": "Daniel Teleginski Camargo",
            "date": "2023-01-11 18:56:59 -0700",
            "line": "13",
            "rev": "^df71167"
          },
          "14": {
            "author": "Daniel Teleginski Camargo",
            "date": "2023-01-11 18:56:59 -0700",
            "line": "14",
            "rev": "^df71167"
          },
          "15": {
            "author": "Daniel Teleginski Camargo",
            "date": "2023-01-11 18:56:59 -0700",
            "line": "15",
            "rev": "^df71167"
          },
          "16": {
            "author": "Daniel Teleginski Camargo",
            "date": "2023-01-11 18:56:59 -0700",
            "line": "16",
            "rev": "^df71167"
          },
          "17": {
            "author": "Daniel Teleginski Camargo",
            "date": "2023-01-11 18:56:59 -0700",
            "line": "17",
            "rev": "^df71167"
          }
        }
      },
      "secondFile": {
        "name": "src/jason/index.html",
        "start": 11,
        "end": 17,
        "startLoc": {
          "line": 11,
          "column": 3,
          "position": 117
        },
        "endLoc": {
          "line": 17,
          "column": 2,
          "position": 180
        },
        "blame": {
          "11": {
            "author": "Daniel Teleginski Camargo",
            "date": "2023-01-11 18:56:59 -0700",
            "line": "11",
            "rev": "^df71167"
          },
          "12": {
            "author": "Daniel Teleginski Camargo",
            "date": "2023-01-11 18:56:59 -0700",
            "line": "12",
            "rev": "^df71167"
          },
          "13": {
            "author": "Daniel Teleginski Camargo",
            "date": "2023-01-11 18:56:59 -0700",
            "line": "13",
            "rev": "^df71167"
          },
          "14": {
            "author": "Daniel Teleginski Camargo",
            "date": "2023-01-11 18:56:59 -0700",
            "line": "14",
            "rev": "^df71167"
          },
          "15": {
            "author": "Daniel Teleginski Camargo",
            "date": "2023-01-11 18:56:59 -0700",
            "line": "15",
            "rev": "^df71167"
          },
          "16": {
            "author": "Daniel Teleginski Camargo",
            "date": "2023-01-11 18:56:59 -0700",
            "line": "16",
            "rev": "^df71167"
          },
          "17": {
            "author": "Daniel Teleginski Camargo",
            "date": "2023-01-11 18:56:59 -0700",
            "line": "17",
            "rev": "^df71167"
          }
        }
      }
    }
  ]
}